{
	"configurations" : 
	[
		{
			"directories" : 
			[
				{
					"build" : ".",
					"jsonFile" : "directory-.-f5ebdc15457944623624.json",
					"minimumCMakeVersion" : 
					{
						"string" : "3.10"
					},
					"projectIndex" : 0,
					"source" : ".",
					"targetIndexes" : 
					[
						0
					]
				}
			],
			"name" : "",
			"projects" : 
			[
				{
					"directoryIndexes" : 
					[
						0
					],
					"name" : "lab5",
					"targetIndexes" : 
					[
						0
					]
				}
			],
			"targets" : 
			[
				{
					"directoryIndex" : 0,
					"id" : "lab5::@6890427a1f51a3e7e1df",
					"jsonFile" : "target-lab5-459c41f156c01b9ec169.json",
					"name" : "lab5",
					"projectIndex" : 0
				}
			]
		}
	],
	"kind" : "codemodel",
	"paths" : 
	{
		"build" : "/home/jj/Documents/Classwork/OS_Classwork/Lab5/build",
		"source" : "/home/jj/Documents/Classwork/OS_Classwork/Lab5"
	},
	"version" : 
	{
		"major" : 2,
		"minor" : 8
	}
}
